
{
    "ClassName": "Turmeric",
    "imageName": "Turmeric.jpg",
    "ScientificName": "Curcuma longa",
    "Location": ["Andhra Pradesh, Tamil Nadu, Orissa, Karnataka, West Bengal, Gujarat, Meghalaya, Maharashtra, Assam"],
    "Information": " It contains a chemical called curcumin, which might reduce swelling." ,
    "Procedure":"Topical Application:\nTurmeric Leaf Paste: Crush fresh turmeric leaves into a paste.\n\nApplication to Skin: Apply the paste directly to swollen or inflamed areas of the skin. The anti-inflammatory properties of curcumin in turmeric leaves may help reduce swelling and alleviate discomfort.\n\nHerbal Compress:\nTurmeric Leaf Infusion: Boil turmeric leaves in water to make an herbal infusion.\nSoaking Cloth: Soak a clean cloth in the cooled turmeric leaf infusion.\n\nApplication to Skin: Apply the soaked cloth as a compress to swollen or inflamed areas. This can help deliver the anti-inflammatory properties of turmeric leaves directly to the affected area.\n\nSteam Inhalation:\nBoiling: Boil turmeric leaves in water to create a steam.\n\nInhalation: Inhale the steam to potentially help alleviate respiratory inflammation and congestion. This method may be particularly beneficial for conditions such as sinusitis or bronchitis."
}
  